algoleap_testing/__init__.py
algoleap_testing/evaluator.py
algoleap_testing-0.1.0.dist-info/METADATA
algoleap_testing-0.1.0.dist-info/WHEEL
algoleap_testing-0.1.0.dist-info/top_level.txt
algoleap_testing-0.1.0.dist-info/RECORD
